README.md
setup.py
qtplot/__init__.py
qtplot/canvas.py
qtplot/colormap.py
qtplot/data.py
qtplot/export.py
qtplot/linecut.py
qtplot/operations.py
qtplot/qtplot.py
qtplot/settings.py
qtplot/util.py
qtplot.egg-info/PKG-INFO
qtplot.egg-info/SOURCES.txt
qtplot.egg-info/dependency_links.txt
qtplot.egg-info/entry_points.txt
qtplot.egg-info/requires.txt
qtplot.egg-info/top_level.txt
qtplot/colormaps/0greyscale.npy
qtplot/colormaps/1band.npy
qtplot/colormaps/4bands.npy
qtplot/colormaps/8bands.npy
qtplot/colormaps/aaron.npy
qtplot/colormaps/afm-hot.npy
qtplot/colormaps/blue-green-pink.npy
qtplot/colormaps/color-gray-print.npy
qtplot/colormaps/hot.npy
qtplot/colormaps/inferno.npy
qtplot/colormaps/magma.npy
qtplot/colormaps/matlabautumn.npy
qtplot/colormaps/matlabbone.npy
qtplot/colormaps/matlabcool.npy
qtplot/colormaps/matlabcopper.npy
qtplot/colormaps/matlabjet.npy
qtplot/colormaps/matlabpink.npy
qtplot/colormaps/matlabspring.npy
qtplot/colormaps/matlabsummer.npy
qtplot/colormaps/matlabwinter.npy
qtplot/colormaps/ocean.npy
qtplot/colormaps/plasma.npy
qtplot/colormaps/rainbow.npy
qtplot/colormaps/ray.npy
qtplot/colormaps/trad-pm3d.npy
qtplot/colormaps/vee.npy
qtplot/colormaps/viol-grn.npy
qtplot/colormaps/viridis.npy
qtplot/colormaps/nanoscope/ns00.npy
qtplot/colormaps/nanoscope/ns01.npy
qtplot/colormaps/nanoscope/ns02.npy
qtplot/colormaps/nanoscope/ns03.npy
qtplot/colormaps/nanoscope/ns04.npy
qtplot/colormaps/nanoscope/ns05.npy
qtplot/colormaps/nanoscope/ns06.npy
qtplot/colormaps/nanoscope/ns07.npy
qtplot/colormaps/nanoscope/ns08.npy
qtplot/colormaps/nanoscope/ns09.npy
qtplot/colormaps/nanoscope/ns10.npy
qtplot/colormaps/nanoscope/ns11.npy
qtplot/colormaps/nanoscope/ns12.npy
qtplot/colormaps/nanoscope/ns13.npy
qtplot/colormaps/nanoscope/ns14.npy
qtplot/colormaps/nanoscope/ns15.npy
qtplot/colormaps/nanoscope/ns16.npy
qtplot/colormaps/nanoscope/ns17.npy
qtplot/colormaps/nanoscope/ns18.npy
qtplot/colormaps/nanoscope/ns19.npy
qtplot/colormaps/nanoscope/ns20.npy
qtplot/colormaps/transform/Apricot.npy
qtplot/colormaps/transform/Carnation.npy
qtplot/colormaps/transform/Ether.npy
qtplot/colormaps/transform/Greyscale_Banded.npy
