Metadata-Version: 1.0
Name: qtplot
Version: 0.1.3
Summary: Data plotting and analysis tool
Home-page: https://github.com/Rubenknex/qtplot
Author: Ruben van Gulik
Author-email: rubenvangulik@gmail.com
License: MIT
Platform: UNKNOWN
